aws_assume_role/__init__.py
aws_assume_role/accounts.py
aws_assume_role/aws_assume_role.py
aws_assume_role/version.py
aws_assume_role/writer.py
bc_onelogin_aws_assume_role-1.8.8.dist-info/LICENSE
bc_onelogin_aws_assume_role-1.8.8.dist-info/METADATA
bc_onelogin_aws_assume_role-1.8.8.dist-info/WHEEL
bc_onelogin_aws_assume_role-1.8.8.dist-info/entry_points.txt
bc_onelogin_aws_assume_role-1.8.8.dist-info/top_level.txt
bc_onelogin_aws_assume_role-1.8.8.dist-info/RECORD
